{
    "headline": "Dragonflies and damselflies  your Green shoots photographs", 
    "text": "   By AlvecoteWood on 12 June 2012  Photograph: Flickr       By PMBrem on 28 May 2012 in Bremen Photograph: Flickr       By Gavin Macrae on 26 May 2012 in Balchraggan, Scotland Photograph: Flickr       By nancy II on 9 June 2012   Photograph: Flickr       By Jane V Adams  on 2 June 2012  Photograph: Flickr       By Marion'09 on June 29, 2012. http://www.flickr.com/photos/41126594@N06/7467073678/in/pool-1490353@N23/.Sympetrum flaveolum.Some facts about dragonflies....- Dragonflies were some of the first winged insects to evolve, some 300 million years ago. Modern dragonflies have wingspans of only two to five inches, but fossil dragonflies have been found with wingspans of up to two feet..- There are more than 5,000 known species of dragonflies, all of which (along with damselflies) belong to the order Odonata, which means toothed one in Greek ....- A single dragonfly can eat 30 to hundreds of mosquitoes per day..- Some adult dragonflies live for only a few weeks while others live up to a year..- Nearly all of the dragonflys head is eye, so they have incredible vision that encompasses almost every angle except right behind them....Source: smithsonianmag.com Photograph: Flickr       By Adam Tacon on 4 June 2012   Photograph: Flickr       By Andy Pritchard on 17 June 2012  Photograph: Flickr       By PMBrem on 26 June 2012 in Bremen Photograph: Flickr       By Penny Bu on 27 June  2012  Photograph: Flickr       By AlvecoteWood on 10 June 2012  Photograph: Flickr       By amythyst_lake on 5 June 2012 in Balsam Lake US,   Photograph: Flickr       By Muzby1801 on 27 April 2012 Photograph: Flickr       By JamesNewman on 27 June 2012 in Wolvercote, England Photograph: Flickr       By devonteg on 20 June 2012 in Withiel Florey, England Photograph: Flickr       By MartinBaldwin on 2 June 2012  Photograph: Flickr       By Cludio Maranho on 1 June 2012  Photograph: Flickr       By harve64 on 2 June 2012  Photograph: Flickr       By TheLilacGrove on 24 May 2012  Photograph: Flickr       By Sylviane Moss on 23 June 2012  Photograph: Flickr       By chriswilson4646  Photograph: Flickr  ", 
    "section": "environment", 
    "gid": "environment/gallery/2012/jul/03/dragonflies-and-damselflies-green-shoots", 
    "wordcount": "0"
}